pandalarell/__init__.py
pandalarell/main.py
pandalarell-0.0.5.1.dist-info/METADATA
pandalarell-0.0.5.1.dist-info/WHEEL
pandalarell-0.0.5.1.dist-info/top_level.txt
pandalarell-0.0.5.1.dist-info/RECORD
