Metadata-Version: 2.1
Name: pandalarell
Version: 0.0.5.1
Summary: Pararell Pandas in the works
Author: Josh Rubanhof
Classifier: Programming Language :: Python :: 3
Classifier: License :: OSI Approved :: MIT License
Classifier: Operating System :: OS Independent
Requires-Python: >=3.6
